<?xml version="1.0" encoding="ISO-8859-1"?>
<monster name="Elder Forest Fury" nameDescription="an elder forest fury" race="blood" experience="330" speed="120">
	<health now="670" max="670"/>
	<look type="569" corpse="22135"/>
	<targetchange interval="4000" chance="10"/>
	<flags>
		<flag summonable="0"/>
		<flag attackable="1"/>
		<flag hostile="1"/>
		<flag illusionable="1"/>
		<flag pushable="0"/>
		<flag convinceable="0"/>
		<flag canPushItems="1"/>
		<flag canPushCreatures="1"/>
		<flag targetDistance="3"/>
		<flag staticAttack="80"/>
		<flag runOnHealth="0"/>
		<flag canWalkOnEnergy="0"/>
		<flag canWalkOnFire="0"/>
		<flag canWalkOnPoison="0"/>
	</flags>
	<attacks>
		<attack name="melee" interval="2000" min="0" max="-125"/>
		<attack name="physical" interval="1500" chance="40" radius="4" target="1" range="7" min="0" max="-100">
			<attribute key="shootEffect" value="huntingspear"/>
			<attribute key="areaEffect" value="greenshimmer"/>
		</attack>
		<attack name="forest fury skill reducer" range="5" interval="2000" chance="20"/>
	</attacks>
	<defenses armor="25" defense="25"/>
	<elements>
		<element firePercent="-5"/>
		<element holyPercent="10"/>
		<element deathPercent="40"/>
	</elements>
	<voices interval="5000" chance="10">
		<voice sentence="To arms, sisters!"/>
		<voice sentence="Feel the wrath of mother forest!"/>
		<voice sentence="By the power of Greenskull!"/>
	</voices>
	<loot>
		<item name="gold coin" countmax="64" chance="89600"/>
		<item name="bolt" countmax="15" chance="45970"/>
		<item name="venison" chance="21480"/>
		<item name="meat" countmax="2" chance="18460"/>
		<item name="piercing bolt" countmax="5" chance="16780"/>
		<item name="elven hoof" chance="12750"/>
		<item name="hunting spear" countmin="2" countmax="2" chance="8050"/>
		<item name="small emerald" chance="3690"/>
		<item name="crossbow" chance="2350"/>
		<item name="raspberry" chance="670"/>
		<item name="terra rod" chance="340"/>
		<item name="bullseye potion" chance="340"/>
		<item name="elvish bow" chance="150"/>
	</loot>
</monster>
