<?xml version="1.0" encoding="UTF-8"?>
<monster name="Cosmic Energy Prism C" nameDescription="cosmic energy prism c" race="undead" experience="840" speed="0" manacost="0">
	<health now="1000" max="1000"/>
	<look typeex="1548" corpse="0"/>
	<targetchange interval="2000" chance="0"/>
	<flags>
		<flag preyable="0"/>
		<flag summonable="0"/>
		<flag attackable="1"/>
		<flag hostile="1"/>
		<flag illusionable="0"/>
		<flag convinceable="0"/>
		<flag pushable="0"/>
		<flag canpushitems="1"/>
		<flag canpushcreatures="1"/>
		<flag targetdistance="1"/>
		<flag staticattack="90"/>
		<flag runonhealth="15"/>
		<flag canwalkonenergy="1"/>
		<flag canwalkonfire="1"/>
		<flag canwalkonpoison="1"/>

	</flags>
	<script>
		<event name="EnergyPrism"/>
	</script>
	<defenses armor="50" defense="50"/>
	<elements>
		<element firePercent="50"/>
		<element earthPercent="50"/>
		<element energyPercent="50"/>
		<element deathPercent="50"/>
		<element physicalPercent="50"/>
		<element holyPercent="50"/>
		<element icePercent="50"/>
	</elements>
	<immunities>
		<immunity paralyze="1"/>
		<immunity invisible="1"/>
	</immunities>
	<voices interval="5000" chance="10">
		<voice sentence="*Zap!*"/>
	</voices>
</monster>
