<?xml version="1.0" encoding="ISO-8859-1"?>
<monster name="Deepling Elite" nameDescription="a deepling elite" race="blood" experience="3000" speed="165">
	<health now="3200" max="3200"/>
	<look type="441" corpse="13712"/>
	<targetchange interval="4000" chance="10"/>
	<flags>
		<flag summonable="0"/>
		<flag attackable="1"/>
		<flag hostile="1"/>
		<flag illusionable="0"/>
		<flag convinceable="0"/>
		<flag pushable="1"/>
		<flag canPushItems="1"/>
		<flag canPushCreatures="1"/>
		<flag targetDistance="0"/>
		<flag staticAttack="90"/>
		<flag runOnHealth="30"/>
		<flag canWalkOnEnergy="0"/>
		<flag canWalkOnPoison="0"/>
		<flag canWalkOnFire="1"/>
	</flags>
	<attacks>
		<attack name="melee" interval="2000" min="0" max="-300"/>
		<attack name="physical" interval="2000" chance="20" range="7" target="1" min="0" max="-225">
			<attribute key="shootEffect" value="largerock"/>
		</attack>
	</attacks>
	<defenses armor="45" defense="45">
		<defense name="healing" interval="2000" chance="10" min="150" max="200">
			<attribute key="areaEffect" value="blueshimmer"/>
		</defense>
	</defenses>
	<elements>
		<element energyPercent="-10"/>
		<element earthPercent="-10"/>
	</elements>
	<immunities>
		<immunity fire="1"/>
		<immunity invisible="1"/>
		<immunity paralyze="1"/>
	</immunities>
	<loot>
		<item name="gold coin" countmax="186" chance="100000"/>
		<item name="great health potion" chance="26000"/>
		<item name="eye of a deepling" chance="25600"/>
		<item name="deepling filet" chance="24910"/>
		<item name="vortex bolt" countmin="1" countmax="5" chance="24570"/>
		<item name="great mana potion" chance="24370"/>
		<item name="deepling warts" chance="24170"/>
		<item name="deeptags" chance="20970"/>
		<item name="deepling ridge" chance="18940"/>
		<item name="small emerald" countmax="2" chance="6860"/>
		<item name="life ring" chance="5620"/>
		<item name="heavy trident" chance="3500"/>
		<item name="fish fin" chance="2420"/>
		<item name="warrior's shield" chance="1130"/>
		<item name="warrior's axe" chance="740"/>
	</loot>
</monster>
