<?xml version="1.0" encoding="UTF-8"?>
<monster name="Falcon Paladin" nameDescription="a falcon paladin" race="blood" experience="7500" speed="330" manacost="0">
	<health now="8500" max="8500"/>
	<look type="1071" head="57" body="94" legs="38" feet="86" addons="2" corpse="32558"/>
	<targetchange interval="4000" chance="10"/>
	<flags>
		<flag summonable="0"/>
		<flag attackable="1"/>
		<flag hostile="1"/>
		<flag illusionable="0"/>
		<flag convinceable="0"/>
		<flag pushable="0"/>
		<flag canpushitems="1"/>
		<flag canpushcreatures="1"/>
		<flag targetdistance="1"/>
		<flag staticattack="70"/>
		<flag runonhealth="0"/>
		<flag canwalkonenergy="0"/>
		<flag canwalkonfire="0"/>
		<flag canwalkonpoison="0"/>
	</flags>
	<attacks>
		<attack name="melee" interval="2000" min="-150" max="-700"/>
		<attack name="physical" interval="2000" chance="50" range="7" min="-50" max="-400">
			<attribute key="shootEffect" value="infernalbolt"/>
		</attack>
		<attack name="physical" interval="2000" chance="20" range="7" min="-50" max="720">
			<attribute key="shootEffect" value="etherealspear"/>
		</attack>
			<attack name="holy" interval="2000" chance="14" length="8" spread="0" min="-50" max="700">
			<attribute key="areaEffect" value="yellowspark"/>
		</attack>
	</attacks>
	<defenses armor="82" defense="50">
		<defense name="healing" interval="2000" chance="20" min="200" max="450">
			<attribute key="areaEffect" value="blueshimmer"/>
		</defense>
	</defenses>
	<elements>
		<element holyPercent="-5" />
	    <element physicalPercent="10"/>
		<element deathPercent="55"/>
	</elements>
	<immunities>
		<immunity paralyze="1"/>
		<immunity invisible="1"/>
	</immunities>
	<voices interval="5000" chance="10">
		<voice sentence="Uuunngh!"/>
	</voices>
	<loot>
 <!-- comun -->
<item name="Small Diamond" countmax="2" chance="41790"/>
<item name="Small Emerald" countmax="2" chance="40620"/>
<item name="Small Amethyst" countmax="2" chance="40080"/>
<item name="Platinum Coin" countmax="5" chance="90000"/>
<item name="Assassin Star" countmax="10" chance="25740"/>
<item name="Great Mana Potion" countmax="3" chance="10000"/>
<item name="Great Health Potion" countmax="3" chance="10000"/>
  <!-- Incomum -->
<item name="Small Ruby" countmax="3" chance="20730"/>
<item name="red Gem" countmax="1" chance="7580"/>
<item name="Onyx Arrow" countmax="15" chance="14630"/>
<item name="Small Topaz" countmax="3" chance="20100"/>
 <!-- semi raro -->
<item id="7633" chance="2260"/>
<item name="Violet Gem" countmax="1" chance="4180"/>
<item name="Green Gem" countmax="1" chance="4860"/>
 <!-- raro -->
<item name="Damaged Armor Plates" countmax="1" chance="1120"/>
<item name="Falcon Crest" countmax="1" chance="730"/>
 <!-- muito raro -->
<item name="Golden Armor" chance="310"/>
<item name="Mastermind Shield" chance="310"/>
	</loot>
</monster>
