<?xml version="1.0" encoding="UTF-8"?>
<monster name="Lonely Snake" nameDescription="a lonely snake" race="blood" experience="0" speed="60">
	<health now="15" max="15"/>
	<look type="28" corpse="21471"/>
	<targetchange interval="4000" chance="0"/>
	<flags>
		<flag summonable="0"/>
		<flag attackable="1"/>
		<flag hostile="1"/>
		<flag illusionable="0"/>
		<flag convinceable="0"/>
		<flag pushable="1"/>
		<flag canPushItems="0"/>
		<flag canPushCreatures="0"/>
		<flag targetDistance="1"/>
		<flag staticAttack="90"/>
		<flag runOnHealth="0"/>
		<flag canWalkOnEnergy="0"/>
		<flag canWalkOnFire="0"/>
	</flags>
	<attacks>
		<attack name="melee" interval="2000" min="0" max="-8" poison="15"/>
	</attacks>
	<defenses armor="0" defense="0"/>
</monster>
